odoo/addons/shopfloor_mobile/README.rst
odoo/addons/shopfloor_mobile/__init__.py
odoo/addons/shopfloor_mobile/__manifest__.py
odoo/addons/shopfloor_mobile/i18n/de.po
odoo/addons/shopfloor_mobile/i18n/es_AR.po
odoo/addons/shopfloor_mobile/i18n/it.po
odoo/addons/shopfloor_mobile/i18n/pt_BR.po
odoo/addons/shopfloor_mobile/i18n/shopfloor_mobile.pot
odoo/addons/shopfloor_mobile/readme/CONTRIBUTORS.md
odoo/addons/shopfloor_mobile/readme/CREDITS.md
odoo/addons/shopfloor_mobile/readme/DESCRIPTION.md
odoo/addons/shopfloor_mobile/readme/HISTORY.md
odoo/addons/shopfloor_mobile/readme/ROADMAP.md
odoo/addons/shopfloor_mobile/readme/USAGE.md
odoo/addons/shopfloor_mobile/static/description/icon.png
odoo/addons/shopfloor_mobile/static/description/index.html
odoo/addons/shopfloor_mobile/static/wms/.gitignore
odoo/addons/shopfloor_mobile/static/wms/src/screen.esm.js
odoo/addons/shopfloor_mobile/static/wms/src/wms_utils.esm.js
odoo/addons/shopfloor_mobile/static/wms/src/components/batch_picking_detail.esm.js
odoo/addons/shopfloor_mobile/static/wms/src/components/batch_picking_line_detail.esm.js
odoo/addons/shopfloor_mobile/static/wms/src/components/manual_select_color.esm.js
odoo/addons/shopfloor_mobile/static/wms/src/components/misc.esm.js
odoo/addons/shopfloor_mobile/static/wms/src/components/packaging-qty-picker.esm.js
odoo/addons/shopfloor_mobile/static/wms/src/components/detail/detail_location.esm.js
odoo/addons/shopfloor_mobile/static/wms/src/components/detail/detail_lot.esm.js
odoo/addons/shopfloor_mobile/static/wms/src/components/detail/detail_operation.esm.js
odoo/addons/shopfloor_mobile/static/wms/src/components/detail/detail_package.esm.js
odoo/addons/shopfloor_mobile/static/wms/src/components/detail/detail_picking.esm.js
odoo/addons/shopfloor_mobile/static/wms/src/components/detail/detail_product.esm.js
odoo/addons/shopfloor_mobile/static/wms/src/components/detail/detail_transfer.esm.js
odoo_addon_shopfloor_mobile-18.0.1.4.0.dist-info/METADATA
odoo_addon_shopfloor_mobile-18.0.1.4.0.dist-info/WHEEL
odoo_addon_shopfloor_mobile-18.0.1.4.0.dist-info/top_level.txt
odoo_addon_shopfloor_mobile-18.0.1.4.0.dist-info/RECORD
