Metadata-Version: 2.1
Name: odoo-addon-shopfloor_mobile
Version: 18.0.1.4.0
Requires-Python: >=3.10
Requires-Dist: odoo-addon-shopfloor==18.0.*
Requires-Dist: odoo-addon-shopfloor_mobile_base==18.0.*
Requires-Dist: odoo==18.0.*
Summary: Mobile frontend for WMS Shopfloor app
Home-page: https://github.com/OCA/stock-logistics-shopfloor
License: AGPL-3
Author: Camptocamp, BCIM, Akretion, Odoo Community Association (OCA)
Author-email: support@odoo-community.org
Classifier: Programming Language :: Python
Classifier: Framework :: Odoo
Classifier: Framework :: Odoo :: 18.0
Classifier: License :: OSI Approved :: GNU Affero General Public License v3
